{"2":{"1":[{"w":"But","s":"G1161"},{"w":"speak","s":"G2980"},{"w":"thou","s":"G4771"},{"w":"the"},{"w":"things"},{"w":"which","s":"G3739"},{"w":"befit","s":"G4241"},{"w":"the"},{"w":"sound","s":"G5198"},{"w":"doctrine","s":"G1319","p":":"}],"2":[{"w":"that","s":"G1511"},{"w":"aged"},{"w":"men","s":"G4246"},{"w":"be","s":"G1511"},{"w":"temperate","s":"G4998","p":","},{"w":"grave","s":"G4586","p":","},{"w":"sober-minded","s":"G4998","p":","},{"w":"sound","s":"G5198"},{"w":"in"},{"w":"faith","s":"G4102","p":","},{"w":"in"},{"w":"love","s":"G26","p":","},{"w":"in"},{"w":"patience","s":"G5281","p":":"}],"3":[{"w":"that","s":"G3361"},{"w":"aged"},{"w":"women","s":"G4247"},{"w":"likewise","s":"G5615"},{"w":"be"},{"w":"reverent","s":"G2412"},{"w":"in","s":"G1722"},{"w":"demeanor","s":"G2688","p":","},{"w":"not","s":"G3361"},{"w":"slanderers","s":"G1228"},{"w":"nor","s":"G3361"},{"w":"enslaved","s":"G1402"},{"w":"to"},{"w":"much","s":"G4183"},{"w":"wine","s":"G3631","p":","},{"w":"teachersof"},{"w":"that"},{"w":"which"},{"w":"is"},{"w":"good","s":"G2567","p":";"}],"4":[{"w":"that","s":"G2443"},{"w":"they"},{"w":"may"},{"w":"train","s":"G4994"},{"w":"None"},{"w":"the"},{"w":"young"},{"w":"women","s":"G3501"},{"w":"G"},{"w":"G"},{"w":"to"},{"w":"love"},{"w":"their"},{"w":"husbands","s":"G5362","p":","},{"w":"to"},{"w":"love"},{"w":"their"},{"w":"children","s":"G5388","p":","}],"5":[{"w":"None"},{"w":"to"},{"w":"be"},{"w":"sober-minded","s":"G4998","p":","},{"w":"chaste","s":"G53","p":","},{"w":"workers"},{"w":"at"},{"w":"home","s":"G3626","p":","},{"w":"kind","s":"G18","p":","},{"w":"being"},{"w":"in"},{"w":"subjection","s":"G5293"},{"w":"to"},{"w":"their"},{"w":"own","s":"G2398"},{"w":"husbands","s":"G435","p":","},{"w":"that","s":"G2443"},{"w":"the"},{"w":"word","s":"G3056"},{"w":"of"},{"w":"God","s":"G2316"},{"w":"be","s":"G987"},{"w":"not","s":"G3361"},{"w":"blasphemed","s":"G987","p":":"}],"6":[{"w":"the"},{"w":"younger"},{"w":"men","s":"G3501"},{"w":"likewise","s":"G5615"},{"w":"exhort","s":"G3870"},{"w":"to"},{"w":"be"},{"w":"sober-minded","s":"G4993","p":":"}],"7":[{"w":"in","s":"G4012"},{"w":"all"},{"w":"things","s":"G3956"},{"w":"showing","s":"G3930"},{"w":"thyself","s":"G4572"},{"w":"an"},{"w":"ensample","s":"G5179"},{"w":"of"},{"w":"good","s":"G2570"},{"w":"works","s":"G2041","p":";"},{"w":"in","s":"G1722"},{"w":"thy"},{"w":"doctrine","s":"G1319"},{"w":"showing"},{"w":"uncorruptness","s":"G90","p":","},{"w":"G"},{"w":"gravity","s":"G4587","p":","}],"8":[{"w":"sound","s":"G5199"},{"w":"speech","s":"G3056","p":","},{"w":"that"},{"w":"cannot"},{"w":"be"},{"w":"condemned","s":"G176","p":";"},{"w":"that","s":"G2443"},{"w":"he"},{"w":"that"},{"w":"is","s":"G3588"},{"w":"of","s":"G1537"},{"w":"the"},{"w":"contrary"},{"w":"part","s":"G1727"},{"w":"may"},{"w":"be"},{"w":"ashamed","s":"G1788","p":","},{"w":"having","s":"G2192"},{"w":"no","s":"G3367"},{"w":"evil"},{"w":"thing","s":"G5337"},{"w":"to"},{"w":"say","s":"G3004"},{"w":"of","s":"G4012"},{"w":"us","s":"G5216","p":"."}],"9":[{"w":"None"},{"w":"Exhortservants","s":"G1401"},{"w":"to"},{"w":"be"},{"w":"in"},{"w":"subjection","s":"G5293"},{"w":"totheirown","s":"G2398"},{"w":"masters","s":"G1203","p":","},{"w":"andto","s":"G1511"},{"w":"bewell-"},{"w":"pleasing","s":"G2101"},{"w":"None"},{"w":"to"},{"w":"them"},{"w":"in","s":"G1722"},{"w":"all","s":"G3956"},{"w":"things","p":";"},{"w":"not","s":"G3361"},{"w":"gainsaying","s":"G483","p":";"}],"10":[{"w":"not","s":"G3361"},{"w":"purloining","s":"G3557","p":","},{"w":"but","s":"G235"},{"w":"showing","s":"G1731"},{"w":"all","s":"G3956"},{"w":"good","s":"G18"},{"w":"fidelity","s":"G4102","p":";"},{"w":"that","s":"G2443"},{"w":"they"},{"w":"may"},{"w":"adorn","s":"G2885"},{"w":"the"},{"w":"doctrine","s":"G1319"},{"w":"of"},{"w":"God","s":"G2316"},{"w":"our","s":"G2257"},{"w":"Saviour","s":"G4990"},{"w":"in","s":"G1722"},{"w":"all"},{"w":"things","s":"G3956","p":"."}],"11":[{"w":"For","s":"G1063"},{"w":"the"},{"w":"grace","s":"G5485"},{"w":"of"},{"w":"God","s":"G2316"},{"w":"hath"},{"w":"appeared","s":"G2014","p":","},{"w":"bringing","s":"G3588"},{"w":"salvation","s":"G4992"},{"w":"to"},{"w":"all","s":"G3956"},{"w":"men","s":"G444","p":","}],"12":[{"w":"instructing","s":"G3811"},{"w":"us","s":"G2248","p":","},{"w":"to"},{"w":"the"},{"w":"intent"},{"w":"that","s":"G2443","p":","},{"w":"denying","s":"G720"},{"w":"ungodliness","s":"G763"},{"w":"and","s":"G2532"},{"w":"worldly","s":"G2886"},{"w":"lusts","s":"G1939","p":","},{"w":"we"},{"w":"shouldlive","s":"G2198"},{"w":"soberly","s":"G4996"},{"w":"and"},{"w":"righteously","s":"G1346"},{"w":"and","s":"G2532"},{"w":"godly","s":"G2153"},{"w":"in","s":"G1722"},{"w":"this","s":"G3588"},{"w":"present","s":"G3568"},{"w":"world","s":"G165","p":";"}],"13":[{"w":"looking"},{"w":"for","s":"G4327"},{"w":"the","s":"G3588"},{"w":"blessed","s":"G3107"},{"w":"hope","s":"G1680"},{"w":"and","s":"G2532"},{"w":"appearing","s":"G2015"},{"w":"of"},{"w":"the"},{"w":"glory","s":"G1391"},{"w":"of"},{"w":"the"},{"w":"great","s":"G3173"},{"w":"God","s":"G2316"},{"w":"and","s":"G2532"},{"w":"our","s":"G2257"},{"w":"Saviour","s":"G4990"},{"w":"Jesus","s":"G2424"},{"w":"Christ","s":"G5547","p":";"}],"14":[{"w":"who","s":"G3739"},{"w":"gave","s":"G1325"},{"w":"himself","s":"G1438"},{"w":"for","s":"G5228"},{"w":"us","s":"G2257","p":","},{"w":"that","s":"G2443"},{"w":"he"},{"w":"might"},{"w":"redeem","s":"G3084"},{"w":"us","s":"G2248"},{"w":"from","s":"G575"},{"w":"all","s":"G3956"},{"w":"iniquity","s":"G458","p":","},{"w":"and","s":"G2532"},{"w":"purify","s":"G2511"},{"w":"unto"},{"w":"himself","s":"G1438"},{"w":"a"},{"w":"people","s":"G2992"},{"w":"for"},{"w":"his"},{"w":"own"},{"w":"possession","s":"G4041","p":","},{"w":"zealous","s":"G2207"},{"w":"of"},{"w":"good","s":"G2570"},{"w":"works","s":"G2041","p":"."}],"15":[{"w":"These"},{"w":"things","s":"G5023"},{"w":"speak","s":"G2980"},{"w":"and","s":"G2532"},{"w":"exhort","s":"G3870"},{"w":"and","s":"G2532"},{"w":"reprove","s":"G1651"},{"w":"with","s":"G3326"},{"w":"all","s":"G3956"},{"w":"authority","s":"G2003","p":"."},{"w":"Let","s":"G4065"},{"w":"no"},{"w":"man","s":"G3367"},{"w":"despise","s":"G4065"},{"w":"thee","s":"G4675","p":"."}]},"3":{"1":[{"w":"Put","s":"G5279"},{"w":"them","s":"G846"},{"w":"in"},{"w":"mind","s":"G5279"},{"w":"to"},{"w":"be"},{"w":"in"},{"w":"subjection"},{"w":"to","s":"G5293"},{"w":"rulers","s":"G746","p":","},{"w":"to","s":"G2532"},{"w":"authorities","s":"G1849","p":","},{"w":"to"},{"w":"be"},{"w":"obedient","s":"G3980","p":","},{"w":"to"},{"w":"be","s":"G1511"},{"w":"ready","s":"G2092"},{"w":"unto","s":"G4314"},{"w":"every","s":"G3956"},{"w":"good","s":"G18"},{"w":"work","s":"G2041","p":","}],"2":[{"w":"to"},{"w":"speak"},{"w":"evil","s":"G987"},{"w":"of"},{"w":"no"},{"w":"man","s":"G3367","p":","},{"w":"not"},{"w":"to"},{"w":"be","s":"G1511"},{"w":"contentious","s":"G269","p":","},{"w":"to"},{"w":"be"},{"w":"gentle","s":"G1933","p":","},{"w":"showing","s":"G1731"},{"w":"all","s":"G3956"},{"w":"meekness","s":"G4236"},{"w":"toward","s":"G4314"},{"w":"all","s":"G3956"},{"w":"men","s":"G444","p":"."}],"3":[{"w":"For","s":"G1063"},{"w":"we","s":"G2249"},{"w":"also","s":"G2532"},{"w":"once","s":"G4218"},{"w":"were","s":"G1510"},{"w":"foolish","s":"G453","p":","},{"w":"disobedient","s":"G545","p":","},{"w":"deceived","s":"G4105","p":","},{"w":"serving","s":"G1398"},{"w":"divers","s":"G4164"},{"w":"lusts","s":"G1939"},{"w":"and","s":"G2532"},{"w":"pleasures","s":"G2237","p":","},{"w":"living","s":"G1236"},{"w":"in","s":"G1722"},{"w":"malice","s":"G2549"},{"w":"and","s":"G2532"},{"w":"envy","s":"G5355","p":","},{"w":"hateful","s":"G4767","p":","},{"w":"hating","s":"G3404"},{"w":"one"},{"w":"another","s":"G240","p":"."}],"4":[{"w":"But","s":"G1161"},{"w":"when","s":"G3753"},{"w":"the"},{"w":"kindness","s":"G5544"},{"w":"of"},{"w":"God","s":"G2316"},{"w":"our","s":"G2257"},{"w":"Saviour","s":"G4990","p":","},{"w":"and","s":"G2532"},{"w":"his"},{"w":"love","s":"G5363"},{"w":"toward"},{"w":"man","s":"G5363","p":","},{"w":"appeared","s":"G2014","p":","}],"5":[{"w":"not","s":"G3756"},{"w":"by","s":"G1537"},{"w":"works","s":"G2041"},{"w":"donein","s":"G1722"},{"w":"righteousness","s":"G1343","p":","},{"w":"which","s":"G3739"},{"w":"we","s":"G2249"},{"w":"did","s":"G4160"},{"w":"ourselves","p":","},{"w":"but","s":"G235"},{"w":"according"},{"w":"to","s":"G2596"},{"w":"his","s":"G846"},{"w":"mercy","s":"G1656"},{"w":"he"},{"w":"saved","s":"G4982"},{"w":"us","s":"G2248","p":","},{"w":"through","s":"G1223"},{"w":"thewashing","s":"G3067"},{"w":"of"},{"w":"regeneration","s":"G3824"},{"w":"and","s":"G2532"},{"w":"renewing","s":"G342"},{"w":"of"},{"w":"the"},{"w":"Holy","s":"G40"},{"w":"Spirit","s":"G4151","p":","}],"6":[{"w":"which","s":"G3739"},{"w":"he"},{"w":"poured","s":"G1632"},{"w":"out"},{"w":"upon","s":"G1909"},{"w":"us","s":"G2248"},{"w":"richly","s":"G4146","p":","},{"w":"through","s":"G1223"},{"w":"Jesus","s":"G2424"},{"w":"Christ","s":"G5547"},{"w":"our","s":"G2257"},{"w":"Saviour","s":"G4990","p":";"}],"7":[{"w":"that","s":"G2443","p":","},{"w":"being"},{"w":"justified","s":"G1344"},{"w":"by"},{"w":"his","s":"G1565"},{"w":"grace","s":"G5485","p":","},{"w":"we"},{"w":"might"},{"w":"be"},{"w":"made","s":"G1096"},{"w":"heirs","s":"G2818"},{"w":"according"},{"w":"to","s":"G2596"},{"w":"the"},{"w":"hope","s":"G1680"},{"w":"of"},{"w":"eternal","s":"G166"},{"w":"life","s":"G2222","p":"."}],"8":[{"w":"Faithful","s":"G4103"},{"w":"is"},{"w":"the"},{"w":"saying","s":"G3056","p":","},{"w":"and","s":"G2532"},{"w":"concerning"},{"w":"these"},{"w":"things","s":"G5130"},{"w":"I"},{"w":"desire","s":"G1014"},{"w":"that","s":"G1226"},{"w":"thou","s":"G4571"},{"w":"affirm"},{"w":"confidently","s":"G1226","p":","},{"w":"to"},{"w":"the"},{"w":"end"},{"w":"that","s":"G2443"},{"w":"they"},{"w":"who"},{"w":"have"},{"w":"believed","s":"G4100"},{"w":"God","s":"G2316"},{"w":"may"},{"w":"be"},{"w":"careful","s":"G5431"},{"w":"to"},{"w":"maintain","s":"G4291"},{"w":"good","s":"G2570"},{"w":"works","s":"G2041","p":"."},{"w":"These"},{"w":"things","s":"G5023"},{"w":"are","s":"G2076"},{"w":"good","s":"G2570"},{"w":"and","s":"G2532"},{"w":"profitable","s":"G5624"},{"w":"unto"},{"w":"men","s":"G444","p":":"}],"9":[{"w":"but","s":"G1161"},{"w":"shun","s":"G4026"},{"w":"foolish","s":"G3474"},{"w":"questionings","s":"G2214","p":","},{"w":"and","s":"G2532"},{"w":"genealogies","s":"G1076","p":","},{"w":"and","s":"G2532"},{"w":"strifes","s":"G2054","p":","},{"w":"and","s":"G2532"},{"w":"fightings","s":"G3163"},{"w":"about"},{"w":"law","s":"G3544","p":";"},{"w":"for","s":"G1063"},{"w":"they"},{"w":"are","s":"G1526"},{"w":"unprofitable","s":"G512"},{"w":"and","s":"G2532"},{"w":"vain","s":"G3152","p":"."}],"10":[{"w":"A"},{"w":"factious","s":"G141"},{"w":"man","s":"G444"},{"w":"after","s":"G3326"},{"w":"a"},{"w":"first","s":"G1520"},{"w":"and","s":"G2532"},{"w":"second","s":"G1208"},{"w":"admonition","s":"G3559"},{"w":"refuse","s":"G3868","p":";"}],"11":[{"w":"knowing","s":"G1492"},{"w":"that","s":"G3754"},{"w":"such","s":"G5108"},{"w":"a"},{"w":"one"},{"w":"is"},{"w":"perverted","s":"G1612","p":","},{"w":"and","s":"G2532"},{"w":"sinneth","s":"G264","p":","},{"w":"being","s":"G5607"},{"w":"self-"},{"w":"condemned","s":"G843","p":"."}],"12":[{"w":"When","s":"G3752"},{"w":"I"},{"w":"shall"},{"w":"send","s":"G3992"},{"w":"Artemas","s":"G734"},{"w":"unto","s":"G4314"},{"w":"thee","s":"G4571","p":","},{"w":"or","s":"G2228"},{"w":"Tychicus","s":"G5190","p":","},{"w":"give"},{"w":"diligence","s":"G4704"},{"w":"to"},{"w":"come","s":"G2064"},{"w":"unto","s":"G4314"},{"w":"me","s":"G3165"},{"w":"to","s":"G1519"},{"w":"Nicopolis","s":"G3533","p":":"},{"w":"for","s":"G1063"},{"w":"there","s":"G1563"},{"w":"I"},{"w":"have"},{"w":"determined","s":"G2919"},{"w":"to"},{"w":"winter","s":"G3914","p":"."}],"13":[{"w":"Set"},{"w":"forward","s":"G4311"},{"w":"Zenas","s":"G2211"},{"w":"the"},{"w":"lawyer","s":"G3544"},{"w":"and","s":"G2532"},{"w":"Apollos","s":"G625"},{"w":"ontheirjourney","s":"G4311"},{"w":"diligently","s":"G4709","p":","},{"w":"that","s":"G2443"},{"w":"nothing","s":"G3367"},{"w":"be"},{"w":"wanting","s":"G3007"},{"w":"unto"},{"w":"them","s":"G846","p":"."}],"14":[{"w":"And","s":"G1161"},{"w":"let","s":"G3129"},{"w":"our"},{"w":"people","s":"G2251"},{"w":"also","s":"G2532"},{"w":"learn","s":"G3129"},{"w":"to"},{"w":"maintain","s":"G4291"},{"w":"good","s":"G2570"},{"w":"works","s":"G2041"},{"w":"for","s":"G1519"},{"w":"necessary","s":"G316"},{"w":"uses","s":"G5532","p":","},{"w":"that","s":"G2443"},{"w":"they"},{"w":"be","s":"G5600"},{"w":"not","s":"G3361"},{"w":"unfruitful","s":"G175","p":"."}],"15":[{"w":"All"},{"w":"that"},{"w":"are","s":"G3956"},{"w":"with","s":"G3326"},{"w":"me","s":"G1700"},{"w":"salute","s":"G782"},{"w":"thee","s":"G4571","p":"."},{"w":"Salute","s":"G782"},{"w":"them"},{"w":"that"},{"w":"love","s":"G5368"},{"w":"us","s":"G2248"},{"w":"in","s":"G1722"},{"w":"faith","s":"G4102","p":"."},{"w":"Grace","s":"G5485"},{"w":"be"},{"w":"with","s":"G3326"},{"w":"you","s":"G5216"},{"w":"all","s":"G3956","p":"."},{"w":"Philemon"}]},"1":{"1":[{"w":"Paul","s":"G3972","p":","},{"w":"a"},{"w":"prisoner","s":"G1198"},{"w":"of"},{"w":"Christ","s":"G5547"},{"w":"Jesus","s":"G2424","p":","},{"w":"and","s":"G2532"},{"w":"Timothy","s":"G5095"},{"w":"our"},{"w":"brother","s":"G80","p":","},{"w":"to"},{"w":"Philemon","s":"G5371"},{"w":"our","s":"G2257"},{"w":"beloved","s":"G27"},{"w":"and","s":"G2532"},{"w":"fellow-worker","s":"G4904","p":","}],"2":[{"w":"and","s":"G2532"},{"w":"to","s":"G27"},{"w":"Apphia","s":"G682"},{"w":"our"},{"w":"sister","p":","},{"w":"and","s":"G2532"},{"w":"to","s":"G27"},{"w":"Archippus","s":"G751"},{"w":"our","s":"G2257"},{"w":"fellow-"},{"w":"soldier","s":"G4961","p":","},{"w":"and","s":"G2532"},{"w":"to"},{"w":"the"},{"w":"church","s":"G1577"},{"w":"in","s":"G2596"},{"w":"thy","s":"G4675"},{"w":"house","s":"G3624","p":":"}],"3":[{"w":"Grace","s":"G5485"},{"w":"to"},{"w":"you","s":"G5213"},{"w":"and","s":"G2532"},{"w":"peace","s":"G1515"},{"w":"from","s":"G575"},{"w":"God","s":"G2316"},{"w":"our","s":"G2257"},{"w":"Father","s":"G3962"},{"w":"and","s":"G2532"},{"w":"the"},{"w":"Lord","s":"G2962"},{"w":"Jesus","s":"G2424"},{"w":"Christ","s":"G5547","p":"."},{"w":"Titus"},{"w":"Philemon"}]}}